iwaratool/__init__.py
iwaratool/iwara.py
iwaratool-0.1.0.dist-info/LICENSE
iwaratool-0.1.0.dist-info/METADATA
iwaratool-0.1.0.dist-info/WHEEL
iwaratool-0.1.0.dist-info/top_level.txt
iwaratool-0.1.0.dist-info/RECORD
