Metadata-Version: 2.1
Name: iwaratool
Version: 0.1.0
Summary: 批量获取iwara的内容
Home-page: http://baiyu.fun
Author: 白色羽毛
Author-email: 1665169869@qq.com
License: LGPL-3.0 License
Platform: all
Classifier: Intended Audience :: Developers
Classifier: Operating System :: OS Independent
Classifier: Natural Language :: Chinese (Simplified)
Classifier: Programming Language :: Python
Classifier: Programming Language :: Python :: 3.6
Classifier: Programming Language :: Python :: 3.7
Classifier: Programming Language :: Python :: 3.8
Classifier: Topic :: Software Development :: Libraries
Requires-Dist: requests (>=2.22.0)
Requires-Dist: setuptools (>=16.0)
